[
    {
        "startTime": 1.0,
        "endTime": 8.0,
        "text": "According to all loaned laws of aviation,"
    },
    {
        "startTime": 11.0,
        "endTime": 20.0,
        "text": "there is no way a bee should be able to try"
    },
    {
        "startTime": 24.0,
        "endTime": 30.0,
        "text": "its things are two fall to get its fat little body"
    },
    {
        "startTime": 31.0,
        "endTime": 36.0,
        "text": "off the ground the bee, off course, flies anyway"
    }
]